odoo8_addon_account_check_deposit-8.0.0.1.1-py2.7-nspkg.pth
odoo8_addon_account_check_deposit-8.0.0.1.1.dist-info/METADATA
odoo8_addon_account_check_deposit-8.0.0.1.1.dist-info/RECORD
odoo8_addon_account_check_deposit-8.0.0.1.1.dist-info/WHEEL
odoo8_addon_account_check_deposit-8.0.0.1.1.dist-info/namespace_packages.txt
odoo8_addon_account_check_deposit-8.0.0.1.1.dist-info/top_level.txt
odoo_addons/account_check_deposit/README.rst
odoo_addons/account_check_deposit/__init__.py
odoo_addons/account_check_deposit/__openerp__.py
odoo_addons/account_check_deposit/data/account_data.xml
odoo_addons/account_check_deposit/data/account_deposit_sequence.xml
odoo_addons/account_check_deposit/i18n/account_check_deposit.pot
odoo_addons/account_check_deposit/i18n/am.po
odoo_addons/account_check_deposit/i18n/ar.po
odoo_addons/account_check_deposit/i18n/bg.po
odoo_addons/account_check_deposit/i18n/bs.po
odoo_addons/account_check_deposit/i18n/ca.po
odoo_addons/account_check_deposit/i18n/ca_ES.po
odoo_addons/account_check_deposit/i18n/cs.po
odoo_addons/account_check_deposit/i18n/da.po
odoo_addons/account_check_deposit/i18n/de.po
odoo_addons/account_check_deposit/i18n/el_GR.po
odoo_addons/account_check_deposit/i18n/en_GB.po
odoo_addons/account_check_deposit/i18n/es.po
odoo_addons/account_check_deposit/i18n/es_AR.po
odoo_addons/account_check_deposit/i18n/es_CL.po
odoo_addons/account_check_deposit/i18n/es_CO.po
odoo_addons/account_check_deposit/i18n/es_CR.po
odoo_addons/account_check_deposit/i18n/es_DO.po
odoo_addons/account_check_deposit/i18n/es_EC.po
odoo_addons/account_check_deposit/i18n/es_ES.po
odoo_addons/account_check_deposit/i18n/es_MX.po
odoo_addons/account_check_deposit/i18n/es_PE.po
odoo_addons/account_check_deposit/i18n/es_PY.po
odoo_addons/account_check_deposit/i18n/es_VE.po
odoo_addons/account_check_deposit/i18n/et.po
odoo_addons/account_check_deposit/i18n/eu.po
odoo_addons/account_check_deposit/i18n/fa.po
odoo_addons/account_check_deposit/i18n/fi.po
odoo_addons/account_check_deposit/i18n/fr.po
odoo_addons/account_check_deposit/i18n/fr_CA.po
odoo_addons/account_check_deposit/i18n/fr_CH.po
odoo_addons/account_check_deposit/i18n/fr_FR.po
odoo_addons/account_check_deposit/i18n/gl.po
odoo_addons/account_check_deposit/i18n/gl_ES.po
